mds_account_statement_fints-4.8.7.dist-info/METADATA
mds_account_statement_fints-4.8.7.dist-info/RECORD
mds_account_statement_fints-4.8.7.dist-info/WHEEL
mds_account_statement_fints-4.8.7.dist-info/entry_points.txt
mds_account_statement_fints-4.8.7.dist-info/top_level.txt
trytond/modules/account_statement_fints/LICENSE
trytond/modules/account_statement_fints/README.rst
trytond/modules/account_statement_fints/__init__.py
trytond/modules/account_statement_fints/bank.py
trytond/modules/account_statement_fints/bank.xml
trytond/modules/account_statement_fints/journal.py
trytond/modules/account_statement_fints/journal.xml
trytond/modules/account_statement_fints/role_access_bank.xml
trytond/modules/account_statement_fints/role_login_edit.xml
trytond/modules/account_statement_fints/statement.py
trytond/modules/account_statement_fints/statement.xml
trytond/modules/account_statement_fints/tryton.cfg
trytond/modules/account_statement_fints/versiondep.txt
trytond/modules/account_statement_fints/wiz_checkaccess.py
trytond/modules/account_statement_fints/wiz_checkaccess.xml
trytond/modules/account_statement_fints/wiz_import.py
trytond/modules/account_statement_fints/wiz_import.xml
trytond/modules/account_statement_fints/locale/de.po
trytond/modules/account_statement_fints/locale/en.po
trytond/modules/account_statement_fints/tests/__init__.py
trytond/modules/account_statement_fints/tests/test_bank.py
trytond/modules/account_statement_fints/tests/testlib.py
trytond/modules/account_statement_fints/view/bank_account_list.xml
trytond/modules/account_statement_fints/view/bank_account_number_form.xml
trytond/modules/account_statement_fints/view/bank_account_number_list.xml
trytond/modules/account_statement_fints/view/bank_form.xml
trytond/modules/account_statement_fints/view/bank_list.xml
trytond/modules/account_statement_fints/view/statement_form.xml
trytond/modules/account_statement_fints/view/statement_journal_form.xml
trytond/modules/account_statement_fints/view/statement_line_form.xml
trytond/modules/account_statement_fints/view/statement_tree.xml
trytond/modules/account_statement_fints/view/wiz_checkbankaccess_checkresult_form.xml
trytond/modules/account_statement_fints/view/wiz_checkbankaccess_enterpin_form.xml
