Metadata-Version: 2.1
Name: mds-account-statement-fints
Version: 4.8.7
Summary: Tryton module for importing bank statements via Internet from your bank using the FinTS-3 protocol.
Home-page: https://www.m-ds.de/
Author: martin-data services
Author-email: service@m-ds.de
License: GPL-3
Keywords: tryton invoice fints bank statement
Platform: UNKNOWN
Classifier: Development Status :: 5 - Production/Stable
Classifier: Environment :: Plugins
Classifier: Framework :: Tryton
Classifier: Intended Audience :: Developers
Classifier: Intended Audience :: Customer Service
Classifier: Intended Audience :: Information Technology
Classifier: Intended Audience :: Financial and Insurance Industry
Classifier: Topic :: Office/Business
Classifier: Topic :: Office/Business :: Financial :: Accounting
Classifier: Natural Language :: German
Classifier: Natural Language :: English
Classifier: Operating System :: OS Independent
Classifier: License :: OSI Approved :: GNU General Public License (GPL)
Classifier: Programming Language :: Python :: 3.4
Classifier: Programming Language :: Python :: 3.5
Classifier: Programming Language :: Python :: 3.6
Requires-Dist: fints (>=1.0.1)
Requires-Dist: mt-940 (>=4.12.2)
Requires-Dist: mds-sqlextension (>=0.1.7)
Requires-Dist: pytz
Requires-Dist: trytond-bank (<4.9,>=4.8)
Requires-Dist: trytond-party (<4.9,>=4.8)
Requires-Dist: trytond-account-statement (<4.9,>=4.8)
Requires-Dist: trytond-account-invoice (<4.9,>=4.8)
Requires-Dist: trytond (<4.9,>=4.8)
